qiskit_ibm_experiment/VERSION.txt
qiskit_ibm_experiment/__init__.py
qiskit_ibm_experiment/exceptions.py
qiskit_ibm_experiment/version.py
qiskit_ibm_experiment/accounts/__init__.py
qiskit_ibm_experiment/accounts/account.py
qiskit_ibm_experiment/accounts/configuration.py
qiskit_ibm_experiment/accounts/exceptions.py
qiskit_ibm_experiment/accounts/management.py
qiskit_ibm_experiment/accounts/storage.py
qiskit_ibm_experiment/client/__init__.py
qiskit_ibm_experiment/client/experiment.py
qiskit_ibm_experiment/client/experiment_rest_adapter.py
qiskit_ibm_experiment/client/local_client.py
qiskit_ibm_experiment/client/session.py
qiskit_ibm_experiment/service/__init__.py
qiskit_ibm_experiment/service/constants.py
qiskit_ibm_experiment/service/device_component.py
qiskit_ibm_experiment/service/experiment_dataclasses.py
qiskit_ibm_experiment/service/ibm_experiment_service.py
qiskit_ibm_experiment/service/utils.py
qiskit_ibm_experiment-0.4.8.dist-info/LICENSE.txt
qiskit_ibm_experiment-0.4.8.dist-info/METADATA
qiskit_ibm_experiment-0.4.8.dist-info/WHEEL
qiskit_ibm_experiment-0.4.8.dist-info/top_level.txt
qiskit_ibm_experiment-0.4.8.dist-info/RECORD
