Metadata-Version: 2.1
Name: qiskit-ibm-experiment
Version: 0.4.8
Summary: Qiskit IBM Experiment service for accessing the quantum experiment interface at IBM
Home-page: https://github.com/Qiskit/qiskit-ibm-experiment
Author: Qiskit Development Team
Author-email: qiskit@us.ibm.com
License: Apache 2.0
Project-URL: Bug Tracker, https://github.com/Qiskit/qiskit-ibm-experiment/issues
Project-URL: Documentation, https://qiskit-extensions.github.io/qiskit-ibm-experiment
Project-URL: Source Code, https://github.com/Qiskit/qiskit-ibm-experiment
Keywords: qiskit sdk quantum api experiment ibm
Platform: UNKNOWN
Classifier: Environment :: Console
Classifier: License :: OSI Approved :: Apache Software License
Classifier: Intended Audience :: Developers
Classifier: Intended Audience :: Science/Research
Classifier: Operating System :: Microsoft :: Windows
Classifier: Operating System :: MacOS
Classifier: Operating System :: POSIX :: Linux
Classifier: Programming Language :: Python :: 3 :: Only
Classifier: Programming Language :: Python :: 3.8
Classifier: Programming Language :: Python :: 3.9
Classifier: Topic :: Scientific/Engineering
Requires-Python: >=3.8
License-File: LICENSE.txt
